paftv/__init__.py
paftv/paftv.py
paftv/lib/__init__.py
paftv/lib/alitv.py
paftv/lib/filter.py
paftv-0.1.1.dist-info/LICENSE
paftv-0.1.1.dist-info/METADATA
paftv-0.1.1.dist-info/WHEEL
paftv-0.1.1.dist-info/entry_points.txt
paftv-0.1.1.dist-info/top_level.txt
paftv-0.1.1.dist-info/RECORD
