Metadata-Version: 2.1
Name: paftv
Version: 0.1.1
Summary: Visualization for PAF files using AliTV
Home-page: https://github.com/MoinSebi/paftv
Author: Sebastian Vorbrugg
Author-email: sebastian.vorbrugg@tuebingen.mpg.de
License: MIT
Platform: UNKNOWN
License-File: LICENSE
Requires-Dist: biopython
